ironBars/__init__.py
ironBars/byteBars.py
ironBars/ironSheets.py
ironbars-0.3.6.dist-info/licenses/LICENSE
ironbars-0.3.6.dist-info/METADATA
ironbars-0.3.6.dist-info/WHEEL
ironbars-0.3.6.dist-info/top_level.txt
ironbars-0.3.6.dist-info/RECORD
