Metadata-Version: 2.4
Name: ironBars
Version: 0.3.6
Summary: A lightweight Python utility library providing handy functions for efficient data handling, CSV management, and Google Sheets integration.
Author-email: Sevrus <b25bs1304@iitj.ac.in>
License: Sevrus IronBars License (2025)
Project-URL: homepage, https://github.com/sevruscorporations/ironbars
Project-URL: repository, https://github.com/sevruscorporations/ironbars
Classifier: Programming Language :: Python :: 3
Classifier: License :: OSI Approved :: MIT License
Classifier: Operating System :: OS Independent
Requires-Python: >=3.10
License-File: LICENSE
Requires-Dist: pandas>=2.0
Requires-Dist: numpy>=2.0
Requires-Dist: requests>=2.2
Requires-Dist: scikit-learn
Requires-Dist: opensimplex
Dynamic: license-file
